cabaret/__init__.py
cabaret/camera.py
cabaret/fits_manager.py
cabaret/focuser.py
cabaret/image.py
cabaret/observatory.py
cabaret/plot.py
cabaret/queries.py
cabaret/site.py
cabaret/sources.py
cabaret/telescope.py
cabaret-0.4.5.dist-info/METADATA
cabaret-0.4.5.dist-info/WHEEL
cabaret-0.4.5.dist-info/licenses/LICENSE
cabaret-0.4.5.dist-info/RECORD
