Metadata-Version: 2.4
Name: cabaret
Version: 0.4.5
Author: Peter Pedersen, Lionel Garcia, David Degen
License: MIT License
License-File: LICENSE
Requires-Python: >=3.11
Requires-Dist: astropy
Requires-Dist: astroquery
Requires-Dist: numpy
Provides-Extra: dev
Requires-Dist: pre-commit; extra == 'dev'
Requires-Dist: pytest; extra == 'dev'
Requires-Dist: ruff; extra == 'dev'
Provides-Extra: docs
Requires-Dist: docformatter[tomli]; extra == 'docs'
Requires-Dist: ipywidgets; extra == 'docs'
Requires-Dist: matplotlib; extra == 'docs'
Requires-Dist: myst-nb; extra == 'docs'
Requires-Dist: numpydoc; extra == 'docs'
Requires-Dist: sphinx; extra == 'docs'
Requires-Dist: sphinx-book-theme; extra == 'docs'
Requires-Dist: sphinx-copybutton; extra == 'docs'
Requires-Dist: sphinx-design; extra == 'docs'
Requires-Dist: toml; extra == 'docs'
Provides-Extra: plot
Requires-Dist: matplotlib; extra == 'plot'
Provides-Extra: test
Requires-Dist: matplotlib; extra == 'test'
Requires-Dist: pytest; extra == 'test'
